easygsvd/__init__.py
easygsvd/gsvd.py
easygsvd/util.py
easygsvd-0.0.3.dist-info/METADATA
easygsvd-0.0.3.dist-info/WHEEL
easygsvd-0.0.3.dist-info/licenses/LICENSE
easygsvd-0.0.3.dist-info/RECORD
